jmcwatch/__init__.py
jmcwatch/cli.py
jmcwatch-0.1.4.dist-info/LICENSE
jmcwatch-0.1.4.dist-info/METADATA
jmcwatch-0.1.4.dist-info/WHEEL
jmcwatch-0.1.4.dist-info/entry_points.txt
jmcwatch-0.1.4.dist-info/top_level.txt
jmcwatch-0.1.4.dist-info/RECORD
