Metadata-Version: 2.1
Name: jmcwatch
Version: 0.1.4
Summary: Watch and compile JMC files. Simply type `jmcwatch` to use.
Author: amandin
Author-email: amawwdin@email.com
License: MIT
License-File: LICENSE
Requires-Dist: click
Requires-Dist: watchdog
